epimodels/__init__.py
epimodels-0.5.2.dist-info/licenses/AUTHORS.rst
epimodels-0.5.2.dist-info/licenses/LICENSE.txt
epimodels-0.5.2.dist-info/METADATA
epimodels-0.5.2.dist-info/WHEEL
epimodels-0.5.2.dist-info/top_level.txt
epimodels-0.5.2.dist-info/RECORD
